{
  "heritageData": [
    {
      "id": 1,
      "title": "陕西皮影戏",
      "category": "民间美术 / 国家级非遗",
      "image": "https://cn.bing.com/images/search?view=detailV2&ccid=2lnd7HNQ&id=B9546D0F9530E9FB65286EA76C90778D64056494&thid=OIP.2lnd7HNQ1OHOMT2-b8C1kAHaE7&mediaurl=https%3a%2f%2fimg95.699pic.com%2fphoto%2f50115%2f4180.jpg_wh860.jpg&exph=573&expw=860&q=%e9%99%95%e8%a5%bf%e7%9a%ae%e5%bd%b1%e6%88%8f&FORM=IRPRST&ck=7E7481C51A2EB1A69AE59792BCC4EAD6&selectedIndex=4&itb=0",
      "desc": "一口叙说千古事，双手对舞百万兵。",
      "detail": "陕西皮影戏起源于汉代，兴盛于唐宋。其造型质朴单纯，富于装饰性，同时又具有精致工巧的艺术特色。表演时，艺人们在白色幕布后面，一边操纵影人，一边用秦腔讲述故事，吼出西北汉子的豪迈。",
      "videoUrl": "https://www.bilibili.com/video/BV1Ax411w7F6/"
    },
    {
      "id": 2,
      "title": "秦腔",
      "category": "传统戏剧 / 国家级非遗",
      "image": "https://cn.bing.com/images/search?view=detailV2&ccid=qugbwyFX&id=D9174AB4CCCF25AE12C6C7B3C92B993733A70E53&thid=OIP.qugbwyFX8LNySDFPIShYRQHaE7&mediaurl=https%3a%2f%2fstatic.jingjiribao.cn%2f2022%2f6%2f14%2f139371_W020220614376771912762.jpeg&exph=1066&expw=1600&q=%e7%a7%a6%e8%85%94&FORM=IRPRST&ck=0A241D64AEC5753EBED7EA6D2DB759E3&selectedIndex=2&itb=0", 
      "desc": "八百里秦川尘土飞扬，三千万老陕齐吼秦腔。",
      "detail": "秦腔，别称\"邦子腔\"，是中国西北最古老的戏剧之一。其特点是高昂激越、强烈急促。听秦腔，能感受到关中八百里秦川的厚重与沧桑，是国家级非物质文化遗产。",
      "videoUrl": "https://www.bilibili.com/video/BV1Qs411N7vK/"
    },
    {
      "id": 3,
      "title": "凤翔泥塑",
      "category": "传统技艺 / 宝鸡",
      "image": "https://cn.bing.com/images/search?view=detailV2&ccid=OpKBJuA5&id=4A63CD51DD315349C0C082A4AEC976B2642C95F2&thid=OIP.OpKBJuA5Vw3n-6BamjvY0QHaE8&mediaurl=https%3a%2f%2fx0.ifengimg.com%2fucms%2f2023_50%2f98606F29742C6CDB0315C15742A32C70C0E98498_size1473_w1200_h800.png&exph=800&expw=1200&q=%e5%87%a4%e7%bf%94%e6%b3%a5%e5%a1%91&FORM=IRPRST&ck=0428489857BCD976F70BA284452140A7&selectedIndex=1&itb=0",
      "desc": "色彩艳丽，造型夸张，寓意驱邪避灾。",
      "detail": "凤翔泥塑汲取了古代石刻、年画、剪纸和刺绣的纹饰，造型夸张，色彩鲜艳，深受人们喜爱。其中以\"挂虎\"和\"坐虎\"最为典型，寓意驱邪避灾，吉祥如意。",
      "videoUrl": "https://www.bilibili.com/video/BV1UW411M7Sg/"
    },
    {
      "id": 4,
      "title": "安塞腰鼓",
      "category": "民俗舞蹈 / 延安",
      "image": "https://cn.bing.com/images/search?view=detailV2&ccid=IWaOESCN&id=86C38B7DEE1DCB4CDAEE48F2D34D122875954035&thid=OIP.IWaOESCNqGRKnEahQ56wzwHaE7&mediaurl=https%3a%2f%2fts1.tc.mm.bing.net%2fth%2fid%2fR-C.21668e11208da8644a9c46a1439eb0cf%3frik%3dNUCVdSgSTdPySA%26riu%3dhttp%253a%252f%252fimg.pconline.com.cn%252fimages%252fupload%252fupc%252ftx%252fphotoblog%252f1006%252f01%252fc16%252f4077920_4077920_1275398392718.jpg%26ehk%3daKBueP3ldmhvabRp0Olxvf201nwMrYWpwh5TYWiNfFg%253d%26risl%3d%26pid%3dImgRaw%26r%3d0&exph=2832&expw=4256&q=%e5%ae%89%e5%a1%9e%e8%85%b0%e9%bc%93&FORM=IRPRST&ck=DA62E156ED239C397663CA60F7846EAA&selectedIndex=5&itb=0安塞腰鼓", 
      "desc": "黄土高原上的\"第一鼓\"，气势磅礴。",
      "detail": "安塞腰鼓是黄土高原上的一种独特的民间大型舞蹈艺术形式，具有2000年以上的历史。表演可由几人或上千人一同进行，磅礴的气势，精湛的技艺，使人叹为观止。",
      "videoUrl": "https://www.bilibili.com/video/BV1Mx411w7nQ/"
    },
    {
      "id": 5,
      "title": "同州梆子",
      "category": "传统戏剧 / 渭南",
      "image": "同州梆子https://cn.bing.com/images/search?view=detailV2&ccid=akWGgnR6&id=0A2003680D0D8BC85C0CF6EED4D2997325A774B0&thid=OIP.akWGgnR6DnN8Jq5V1n5jIwHaF8&mediaurl=https%3a%2f%2fts1.tc.mm.bing.net%2fth%2fid%2fR-C.6a458682747a0e737c26ae55d67e6323%3frik%3dsHSnJXOZ0tTu9g%26riu%3dhttp%253a%252f%252fwww.whysb.org%252fwhysb%252f20171117%252fhtml%252fc3b85411da0154c04e881933a3e8dddb_img_671_817_196_158.jpg%26ehk%3dPBjtevoUe1X76gg7%252bRbKz1HfSjnkrPrQqBFagZLBTLo%253d%26risl%3d%26pid%3dImgRaw%26r%3d0&exph=600&expw=748&q=%e5%90%8c%e5%b7%9e%e6%a2%86%e5%ad%90&FORM=IRPRST&ck=17001E83A5EA80CEFEB0419621387ABD&selectedIndex=1&itb=0",
      "desc": "秦腔的鼻祖，唱腔激越豪放。",
      "detail": "同州梆子是陕西省东府渭南地区的地方戏曲剧种，是秦腔的前身。它保留了更多古老的音韵和表演程式，具有极高的艺术研究价值。",
      "videoUrl": "#"
    },
    {
      "id": 6,
      "title": "耀州窑陶瓷",
      "category": "传统技艺 / 铜川",
      "image": "耀州窑瓷器https://cn.bing.com/images/search?view=detailV2&ccid=TmPQKYiQ&id=E04F002D822BCC35234A5432EFF50127DA4F1B1C&thid=OIP.TmPQKYiQlNe8ONiO6wsc7QHaHa&mediaurl=https%3a%2f%2fn.sinaimg.cn%2fsinacn20112%2f560%2fw1080h1080%2f20190926%2f0fb4-ifaench4991248.jpg&exph=1080&expw=1080&q=%e8%80%80%e5%b7%9e%e7%aa%91%e7%93%b7%e5%99%a8&FORM=IRPRST&ck=EB46720F0B271A001999A509AD67C623&selectedIndex=4&itb=0",
      "desc": "巧如范金，精比琢玉，北方青瓷代表。",
      "detail": "耀州窑是中国传统制琴工艺中的珍品，宋代六大窑系。其刀法犀利流畅，线条刚劲有力，素有\"北方青瓷之冠\"的美誉。",
      "videoUrl": "#"
    }
  ],
  "seasonalData": {
    "lichun": {
      "name": "立春",
      "date": "2月3日-5日",
      "color": "#52c41a",
      "intro": "立春，为二十四节气之首。立，是\"开始\"之意；春，代表着温暖、生长。立春不仅是春天的开始，也是一年农事活动的开端。陕西民间有\"咬春\"的习俗，吃春饼、嚼萝卜，祈求身体健康，五谷丰登。",
      "foods": [
        { "name": "春饼卷素", "calories": 320, "desc": "薄饼卷土豆丝、豆芽，寓意咬住春天", "icon": "?" },
        { "name": "凉拌萝卜丝", "calories": 80, "desc": "清脆爽口，顺气消食，谓之\"咬春\"", "icon": "?" },
        { "name": "韭菜炒鸡蛋", "calories": 260, "desc": "春令时鲜，助阳生发", "icon": "?" }
      ]
    },
    "qingming": {
      "name": "清明",
      "date": "4月4日-6日",
      "color": "#13c2c2",
      "intro": "清明时节雨纷纷，万物生长此时洁净而明清。此时节气温转暖，但早晚仍有凉意。饮食宜温和，多吃柔肝养肺的食物。陕西关中地区有吃\"寒食\"的遗风，如凉皮、凉面等。",
      "foods": [
        { "name": "青团", "calories": 220, "desc": "艾草汁和面，清淡幽香，软糯可口", "icon": "?" },
        { "name": "秦镇凉皮", "calories": 280, "desc": "清明吃凉，酸辣开胃，关中特色", "icon": "?" },
        { "name": "螺蛳肉", "calories": 150, "desc": "清明螺，抵只鹅，肉质肥美", "icon": "?" }
      ]
    },
    "dashu": {
      "name": "大暑",
      "date": "7月22日-24日",
      "color": "#fa8c16",
      "intro": "大暑是全年最热的节气，\"湿热交蒸\"在此时达到顶点。饮食应以清热解暑、健脾利湿为主。老陕人喜欢在夏天喝绿豆汤、吃浆水鱼鱼，既解暑又开胃。",
      "foods": [
        { "name": "绿豆百合汤", "calories": 120, "desc": "消暑止渴，清心安神", "icon": "?" },
        { "name": "浆水鱼鱼", "calories": 180, "desc": "酸香爽滑，也是陕西夏日消暑神器", "icon": "?" },
        { "name": "苦瓜炒肉", "calories": 240, "desc": "苦味入心，清热祛火", "icon": "?" }
      ]
    },
    "dongzhi": {
      "name": "冬至",
      "date": "12月21日-23日",
      "color": "#1890ff",
      "intro": "冬至是\"阴极之至，阳气始生\"的重要节气。在陕西，冬至地位极高，所谓\"冬至大如年\"。最核心的习俗就是吃饺子，寓意消寒，不冻耳朵；陕北地区则有喝羊肉汤的习惯，以此温补阳气。",
      "foods": [
        { "name": "酸汤水饺", "calories": 450, "desc": "冬至不端饺子碗，冻掉耳朵没人管", "icon": "?" },
        { "name": "铁锅炖羊肉", "calories": 500, "desc": "温中暖肾，抵御严寒", "icon": "?" },
        { "name": "八宝粥", "calories": 300, "desc": "五谷杂粮，健脾养胃", "icon": "?" }
      ]
    }
  }
}
